{
	"info": {
		"_postman_id": "602e126e-8b0f-43fa-9e1f-384cc3f4188d",
		"name": "Spotnu",
		"schema": "https://schema.getpostman.com/json/collection/v2.1.0/collection.json"
	},
	"item": [
		{
			"name": "creat playlists rock gringo",
			"request": {
				"method": "POST",
				"header": [
					{
						"key": "Authorization",
						"value": "kelly-knoblauch-dumont",
						"type": "text"
					}
				],
				"body": {
					"mode": "raw",
					"raw": "{\n    \"name\": \"D'yer Mak'er\",\n    \"artist\": \"Led Zeppelin\",\n    \"url\": \"https://www.youtube.com/watch?v=_pFZz3OXcMs\"\n}",
					"options": {
						"raw": {
							"language": "json"
						}
					}
				},
				"url": {
					"raw": "https://us-central1-labenu-apis.cloudfunctions.net/labefy/playlists",
					"protocol": "https",
					"host": [
						"us-central1-labenu-apis",
						"cloudfunctions",
						"net"
					],
					"path": [
						"labefy",
						"playlists"
					]
				}
			},
			"response": []
		},
		{
			"name": "create playlist rock nacional",
			"request": {
				"method": "POST",
				"header": [
					{
						"key": "Authorization",
						"value": "kelly-knoblauch-dumont",
						"type": "text"
					}
				],
				"body": {
					"mode": "raw",
					"raw": "{\n    \"name\": \"João Pessoa\",\n    \"artist\": \"Raimundos\",\n    \"url\": \"https://www.youtube.com/watch?v=FC5D4dCktBA\"\n}",
					"options": {
						"raw": {
							"language": "json"
						}
					}
				},
				"url": {
					"raw": "https://us-central1-labenu-apis.cloudfunctions.net/labefy/playlists?",
					"protocol": "https",
					"host": [
						"us-central1-labenu-apis",
						"cloudfunctions",
						"net"
					],
					"path": [
						"labefy",
						"playlists"
					],
					"query": [
						{
							"key": "",
							"value": null
						}
					]
				}
			},
			"response": []
		},
		{
			"name": "creat playlist old but gold",
			"request": {
				"method": "POST",
				"header": [
					{
						"key": "Authorization",
						"value": "kelly-knoblauch-dumont",
						"type": "text"
					}
				],
				"body": {
					"mode": "raw",
					"raw": "{\n    \"name\": \"Angel\",\n    \"artist\": \"Madonna\",\n    \"url\": \"https://www.youtube.com/watch?v=APO9ZKtiy1c\"\n\n}",
					"options": {
						"raw": {
							"language": "json"
						}
					}
				},
				"url": {
					"raw": "https://us-central1-labenu-apis.cloudfunctions.net/labefy/playlists",
					"protocol": "https",
					"host": [
						"us-central1-labenu-apis",
						"cloudfunctions",
						"net"
					],
					"path": [
						"labefy",
						"playlists"
					]
				}
			},
			"response": []
		}
	],
	"protocolProfileBehavior": {}
}